alchemical/__init__.py
alchemical/aio.py
alchemical/core.py
alchemical/flask.py
alchemical/alembic/__init__.py
alchemical/alembic/cli.py
alchemical/alembic/env.py
alchemical/alembic/templates/generic/README
alchemical/alembic/templates/generic/alembic.ini.mako
alchemical/alembic/templates/generic/env.py
alchemical/alembic/templates/generic/script.py.mako
alchemical-1.0.2.dist-info/LICENSE
alchemical-1.0.2.dist-info/METADATA
alchemical-1.0.2.dist-info/WHEEL
alchemical-1.0.2.dist-info/top_level.txt
alchemical-1.0.2.dist-info/RECORD
