Metadata-Version: 2.1
Name: alchemical
Version: 1.0.2
Summary: Modern SQLAlchemy simplified
Author-email: Miguel Grinberg <miguel.grinberg@gmail.com>
Project-URL: Homepage, https://github.com/miguelgrinberg/alchemical
Project-URL: Bug Tracker, https://github.com/miguelgrinberg/alchemical/issues
Classifier: Intended Audience :: Developers
Classifier: Programming Language :: Python :: 3
Classifier: License :: OSI Approved :: MIT License
Classifier: Operating System :: OS Independent
Requires-Python: >=3.7
License-File: LICENSE
Requires-Dist: sqlalchemy>=1.4.24
Provides-Extra: docs
Requires-Dist: sphinx; extra == "docs"
